zerlib/__init__.py
zerlib/zerlib.py
zerlib-0.1.1.dist-info/METADATA
zerlib-0.1.1.dist-info/WHEEL
zerlib-0.1.1.dist-info/top_level.txt
zerlib-0.1.1.dist-info/RECORD
