Metadata-Version: 2.1
Name: zerlib
Version: 0.1.1
Summary: • Script Very Nice To Helping Programmer .
Home-page: 
Author: ZER TOOLS
Author-email: 
Project-URL: Bug Tracker, https://github.com/pypa/sampleproject/issues
Classifier: Programming Language :: Python :: 3
Classifier: License :: OSI Approved :: MIT License
Classifier: Operating System :: OS Independent
Requires-Python: >=3.9
